{
  "cascadeEnabled" : false,
  "description" : "eshopping",
  "draft" : false,
  "name" : "eshopping",
  "packageName" : "com.wavemaker.sampleapps.wavekart.eshopping",
  "tables" : [ {
    "catalog" : "PUBLIC",
    "columns" : [ {
      "columnValue" : {
        "insertable" : true,
        "updatable" : true,
        "defaultValue" : null,
        "type" : "user-defined"
      },
      "constraintList" : null,
      "fieldName" : "userId",
      "foreignKey" : false,
      "generatorType" : "identity",
      "generatorValue" : null,
      "hidden" : false,
      "javaType" : "integer",
      "length" : 255,
      "name" : "USER_ID",
      "nullable" : false,
      "oldName" : "USER_ID",
      "partOfAnyRelation" : false,
      "partOfForeignKey" : false,
      "partOfPrimaryKey" : true,
      "partOfUniqueKey" : true,
      "period" : false,
      "precision" : 10,
      "primaryKey" : true,
      "scale" : 0,
      "sequenceSchema" : null,
      "sqlType" : "number",
      "unique" : true
    }, {
      "columnValue" : {
        "insertable" : true,
        "updatable" : true,
        "defaultValue" : null,
        "type" : "user-defined"
      },
      "constraintList" : null,
      "fieldName" : "userName",
      "foreignKey" : false,
      "generatorType" : "assigned",
      "generatorValue" : null,
      "hidden" : false,
      "javaType" : "string",
      "length" : 255,
      "name" : "USER_NAME",
      "nullable" : false,
      "oldName" : "USER_NAME",
      "partOfAnyRelation" : false,
      "partOfForeignKey" : false,
      "partOfPrimaryKey" : false,
      "partOfUniqueKey" : false,
      "period" : false,
      "precision" : 19,
      "primaryKey" : false,
      "scale" : 2,
      "sequenceSchema" : null,
      "sqlType" : "string",
      "unique" : false
    }, {
      "columnValue" : {
        "insertable" : true,
        "updatable" : true,
        "defaultValue" : null,
        "type" : "user-defined"
      },
      "constraintList" : null,
      "fieldName" : "password",
      "foreignKey" : false,
      "generatorType" : "assigned",
      "generatorValue" : null,
      "hidden" : false,
      "javaType" : "string",
      "length" : 255,
      "name" : "PASSWORD",
      "nullable" : false,
      "oldName" : "PASSWORD",
      "partOfAnyRelation" : false,
      "partOfForeignKey" : false,
      "partOfPrimaryKey" : false,
      "partOfUniqueKey" : false,
      "period" : false,
      "precision" : 19,
      "primaryKey" : false,
      "scale" : 2,
      "sequenceSchema" : null,
      "sqlType" : "string",
      "unique" : false
    }, {
      "columnValue" : {
        "insertable" : true,
        "updatable" : true,
        "defaultValue" : null,
        "type" : "user-defined"
      },
      "constraintList" : null,
      "fieldName" : "phoneNumber",
      "foreignKey" : false,
      "generatorType" : "assigned",
      "generatorValue" : null,
      "hidden" : false,
      "javaType" : "string",
      "length" : 50,
      "name" : "PHONE_NUMBER",
      "nullable" : false,
      "oldName" : "PHONE_NUMBER",
      "partOfAnyRelation" : false,
      "partOfForeignKey" : false,
      "partOfPrimaryKey" : false,
      "partOfUniqueKey" : false,
      "period" : false,
      "precision" : 19,
      "primaryKey" : false,
      "scale" : 2,
      "sequenceSchema" : null,
      "sqlType" : "string",
      "unique" : false
    }, {
      "columnValue" : {
        "insertable" : true,
        "updatable" : true,
        "defaultValue" : null,
        "type" : "user-defined"
      },
      "constraintList" : null,
      "fieldName" : "emailAddress",
      "foreignKey" : false,
      "generatorType" : "assigned",
      "generatorValue" : null,
      "hidden" : false,
      "javaType" : "string",
      "length" : 255,
      "name" : "EMAIL_ADDRESS",
      "nullable" : false,
      "oldName" : "EMAIL_ADDRESS",
      "partOfAnyRelation" : false,
      "partOfForeignKey" : false,
      "partOfPrimaryKey" : false,
      "partOfUniqueKey" : true,
      "period" : false,
      "precision" : 19,
      "primaryKey" : false,
      "scale" : 2,
      "sequenceSchema" : null,
      "sqlType" : "string",
      "unique" : true
    }, {
      "columnValue" : {
        "insertable" : true,
        "updatable" : true,
        "defaultValue" : null,
        "type" : "user-defined"
      },
      "constraintList" : null,
      "fieldName" : "role",
      "foreignKey" : false,
      "generatorType" : "assigned",
      "generatorValue" : null,
      "hidden" : false,
      "javaType" : "string",
      "length" : 25,
      "name" : "ROLE",
      "nullable" : false,
      "oldName" : "ROLE",
      "partOfAnyRelation" : false,
      "partOfForeignKey" : false,
      "partOfPrimaryKey" : false,
      "partOfUniqueKey" : false,
      "period" : false,
      "precision" : 19,
      "primaryKey" : false,
      "scale" : 2,
      "sequenceSchema" : null,
      "sqlType" : "string",
      "unique" : false
    } ],
    "constraints" : [ {
      "columns" : [ "EMAIL_ADDRESS" ],
      "composite" : false,
      "name" : "SYS_IDX_SYS_CT_10112_10120",
      "schemaName" : null,
      "type" : "UNIQUE",
      "virtual" : false
    } ],
    "entityName" : "UserDetails",
    "filter" : null,
    "fullyQualifiedName" : "com.wavemaker.sampleapps.wavekart.eshopping.UserDetails",
    "ignoreRefreshAfterInsert" : false,
    "name" : "USER_DETAILS",
    "oldName" : "USER_DETAILS",
    "primaryKey" : {
      "columns" : [ "USER_ID" ],
      "composite" : false,
      "generator" : {
        "generatorType" : "identity",
        "generatorValue" : null,
        "schemaName" : null
      },
      "name" : "SYS_PK_10106",
      "virtual" : false
    },
    "relations" : [ ],
    "schema" : "PUBLIC",
    "temporals" : [ ],
    "type" : "TABLE"
  }, {
    "catalog" : "PUBLIC",
    "columns" : [ {
      "columnValue" : {
        "insertable" : true,
        "updatable" : true,
        "defaultValue" : null,
        "type" : "user-defined"
      },
      "constraintList" : null,
      "fieldName" : "productId",
      "foreignKey" : false,
      "generatorType" : "identity",
      "generatorValue" : null,
      "hidden" : false,
      "javaType" : "integer",
      "length" : 255,
      "name" : "PRODUCT_ID",
      "nullable" : false,
      "oldName" : "PRODUCT_ID",
      "partOfAnyRelation" : false,
      "partOfForeignKey" : false,
      "partOfPrimaryKey" : true,
      "partOfUniqueKey" : true,
      "period" : false,
      "precision" : 10,
      "primaryKey" : true,
      "scale" : 0,
      "sequenceSchema" : null,
      "sqlType" : "number",
      "unique" : true
    }, {
      "columnValue" : {
        "insertable" : true,
        "updatable" : true,
        "defaultValue" : null,
        "type" : "user-defined"
      },
      "constraintList" : null,
      "fieldName" : "productName",
      "foreignKey" : false,
      "generatorType" : "assigned",
      "generatorValue" : null,
      "hidden" : false,
      "javaType" : "string",
      "length" : 255,
      "name" : "PRODUCT_NAME",
      "nullable" : false,
      "oldName" : "PRODUCT_NAME",
      "partOfAnyRelation" : false,
      "partOfForeignKey" : false,
      "partOfPrimaryKey" : false,
      "partOfUniqueKey" : false,
      "period" : false,
      "precision" : 19,
      "primaryKey" : false,
      "scale" : 2,
      "sequenceSchema" : null,
      "sqlType" : "string",
      "unique" : false
    }, {
      "columnValue" : {
        "insertable" : true,
        "updatable" : true,
        "defaultValue" : null,
        "type" : "user-defined"
      },
      "constraintList" : null,
      "fieldName" : "productDescription",
      "foreignKey" : false,
      "generatorType" : "assigned",
      "generatorValue" : null,
      "hidden" : false,
      "javaType" : "string",
      "length" : 255,
      "name" : "PRODUCT_DESCRIPTION",
      "nullable" : false,
      "oldName" : "PRODUCT_DESCRIPTION",
      "partOfAnyRelation" : false,
      "partOfForeignKey" : false,
      "partOfPrimaryKey" : false,
      "partOfUniqueKey" : false,
      "period" : false,
      "precision" : 19,
      "primaryKey" : false,
      "scale" : 2,
      "sequenceSchema" : null,
      "sqlType" : "string",
      "unique" : false
    }, {
      "columnValue" : {
        "insertable" : true,
        "updatable" : true,
        "defaultValue" : null,
        "type" : "user-defined"
      },
      "constraintList" : null,
      "fieldName" : "category",
      "foreignKey" : false,
      "generatorType" : "assigned",
      "generatorValue" : null,
      "hidden" : false,
      "javaType" : "string",
      "length" : 255,
      "name" : "CATEGORY",
      "nullable" : false,
      "oldName" : "CATEGORY",
      "partOfAnyRelation" : false,
      "partOfForeignKey" : false,
      "partOfPrimaryKey" : false,
      "partOfUniqueKey" : false,
      "period" : false,
      "precision" : 19,
      "primaryKey" : false,
      "scale" : 2,
      "sequenceSchema" : null,
      "sqlType" : "string",
      "unique" : false
    }, {
      "columnValue" : {
        "insertable" : true,
        "updatable" : true,
        "defaultValue" : null,
        "type" : "user-defined"
      },
      "constraintList" : null,
      "fieldName" : "imageUrl",
      "foreignKey" : false,
      "generatorType" : "assigned",
      "generatorValue" : null,
      "hidden" : false,
      "javaType" : "string",
      "length" : 255,
      "name" : "IMAGE_URL",
      "nullable" : false,
      "oldName" : "IMAGE_URL",
      "partOfAnyRelation" : false,
      "partOfForeignKey" : false,
      "partOfPrimaryKey" : false,
      "partOfUniqueKey" : false,
      "period" : false,
      "precision" : 19,
      "primaryKey" : false,
      "scale" : 2,
      "sequenceSchema" : null,
      "sqlType" : "string",
      "unique" : false
    }, {
      "columnValue" : {
        "insertable" : true,
        "updatable" : true,
        "defaultValue" : null,
        "type" : "user-defined"
      },
      "constraintList" : null,
      "fieldName" : "price",
      "foreignKey" : false,
      "generatorType" : "assigned",
      "generatorValue" : null,
      "hidden" : false,
      "javaType" : "big_decimal",
      "length" : 255,
      "name" : "PRICE",
      "nullable" : false,
      "oldName" : "PRICE",
      "partOfAnyRelation" : false,
      "partOfForeignKey" : false,
      "partOfPrimaryKey" : false,
      "partOfUniqueKey" : false,
      "period" : false,
      "precision" : 64,
      "primaryKey" : false,
      "scale" : 9,
      "sequenceSchema" : null,
      "sqlType" : "number",
      "unique" : false
    } ],
    "constraints" : [ ],
    "entityName" : "ProductDetails",
    "filter" : null,
    "fullyQualifiedName" : "com.wavemaker.sampleapps.wavekart.eshopping.ProductDetails",
    "ignoreRefreshAfterInsert" : false,
    "name" : "PRODUCT_DETAILS",
    "oldName" : "PRODUCT_DETAILS",
    "primaryKey" : {
      "columns" : [ "PRODUCT_ID" ],
      "composite" : false,
      "generator" : {
        "generatorType" : "identity",
        "generatorValue" : null,
        "schemaName" : null
      },
      "name" : "SYS_PK_10092",
      "virtual" : false
    },
    "relations" : [ ],
    "schema" : "PUBLIC",
    "temporals" : [ ],
    "type" : "TABLE"
  }, {
    "catalog" : "PUBLIC",
    "columns" : [ {
      "columnValue" : {
        "insertable" : true,
        "updatable" : true,
        "defaultValue" : null,
        "type" : "user-defined"
      },
      "constraintList" : null,
      "fieldName" : "productId",
      "foreignKey" : true,
      "generatorType" : "assigned",
      "generatorValue" : null,
      "hidden" : false,
      "javaType" : "integer",
      "length" : 255,
      "name" : "PRODUCT_ID",
      "nullable" : false,
      "oldName" : "PRODUCT_ID",
      "partOfAnyRelation" : true,
      "partOfForeignKey" : true,
      "partOfPrimaryKey" : true,
      "partOfUniqueKey" : true,
      "period" : false,
      "precision" : 10,
      "primaryKey" : true,
      "scale" : 0,
      "sequenceSchema" : null,
      "sqlType" : "number",
      "unique" : true
    }, {
      "columnValue" : {
        "insertable" : true,
        "updatable" : true,
        "defaultValue" : null,
        "type" : "user-defined"
      },
      "constraintList" : null,
      "fieldName" : "quantity",
      "foreignKey" : false,
      "generatorType" : "assigned",
      "generatorValue" : null,
      "hidden" : false,
      "javaType" : "integer",
      "length" : 255,
      "name" : "QUANTITY",
      "nullable" : true,
      "oldName" : "QUANTITY",
      "partOfAnyRelation" : false,
      "partOfForeignKey" : false,
      "partOfPrimaryKey" : false,
      "partOfUniqueKey" : false,
      "period" : false,
      "precision" : 10,
      "primaryKey" : false,
      "scale" : 0,
      "sequenceSchema" : null,
      "sqlType" : "number",
      "unique" : false
    }, {
      "columnValue" : {
        "insertable" : true,
        "updatable" : true,
        "defaultValue" : null,
        "type" : "user-defined"
      },
      "constraintList" : null,
      "fieldName" : "status",
      "foreignKey" : false,
      "generatorType" : "assigned",
      "generatorValue" : null,
      "hidden" : false,
      "javaType" : "string",
      "length" : 255,
      "name" : "STATUS",
      "nullable" : false,
      "oldName" : "STATUS",
      "partOfAnyRelation" : false,
      "partOfForeignKey" : false,
      "partOfPrimaryKey" : false,
      "partOfUniqueKey" : false,
      "period" : false,
      "precision" : 19,
      "primaryKey" : false,
      "scale" : 2,
      "sequenceSchema" : null,
      "sqlType" : "string",
      "unique" : false
    } ],
    "constraints" : [ ],
    "entityName" : "ProductInventory",
    "filter" : null,
    "fullyQualifiedName" : "com.wavemaker.sampleapps.wavekart.eshopping.ProductInventory",
    "ignoreRefreshAfterInsert" : false,
    "name" : "PRODUCT_INVENTORY",
    "oldName" : "PRODUCT_INVENTORY",
    "primaryKey" : {
      "columns" : [ "PRODUCT_ID" ],
      "composite" : false,
      "generator" : {
        "generatorType" : "assigned",
        "generatorValue" : null,
        "schemaName" : null
      },
      "name" : "SYS_PK_10122",
      "virtual" : false
    },
    "relations" : [ {
      "cardinality" : "OneToOne",
      "cascadeEnabled" : true,
      "cascadeOptions" : {
        "cascadeRemove" : "REMOVE",
        "cascadeReplace" : false
      },
      "columnsUniqueKey" : false,
      "composite" : false,
      "fetchOptions" : {
        "fetch" : true,
        "columnsFilter" : [ ]
      },
      "fieldName" : "productDetails",
      "ignored" : false,
      "mappings" : [ {
        "sourceColumn" : "PRODUCT_ID",
        "targetColumn" : "PRODUCT_ID"
      } ],
      "name" : "SYS_FK_10124",
      "parentFetchOptions" : {
        "fetch" : false,
        "columnsFilter" : [ ]
      },
      "primary" : true,
      "selfRelation" : false,
      "sourceColumnsNotUniqueKey" : true,
      "sourceTable" : "PRODUCT_INVENTORY",
      "targetColumnsUniqueKey" : false,
      "targetTable" : "PRODUCT_DETAILS",
      "valid" : true,
      "virtual" : false
    } ],
    "schema" : "PUBLIC",
    "temporals" : [ ],
    "type" : "TABLE"
  }, {
    "catalog" : "PUBLIC",
    "columns" : [ {
      "columnValue" : {
        "insertable" : true,
        "updatable" : true,
        "defaultValue" : null,
        "type" : "user-defined"
      },
      "constraintList" : null,
      "fieldName" : "cartId",
      "foreignKey" : true,
      "generatorType" : "assigned",
      "generatorValue" : null,
      "hidden" : false,
      "javaType" : "integer",
      "length" : 255,
      "name" : "CART_ID",
      "nullable" : false,
      "oldName" : "CART_ID",
      "partOfAnyRelation" : true,
      "partOfForeignKey" : true,
      "partOfPrimaryKey" : true,
      "partOfUniqueKey" : false,
      "period" : false,
      "precision" : 10,
      "primaryKey" : false,
      "scale" : 0,
      "sequenceSchema" : null,
      "sqlType" : "number",
      "unique" : false
    }, {
      "columnValue" : {
        "insertable" : true,
        "updatable" : true,
        "defaultValue" : null,
        "type" : "user-defined"
      },
      "constraintList" : null,
      "fieldName" : "productId",
      "foreignKey" : true,
      "generatorType" : "assigned",
      "generatorValue" : null,
      "hidden" : false,
      "javaType" : "integer",
      "length" : 255,
      "name" : "PRODUCT_ID",
      "nullable" : false,
      "oldName" : "PRODUCT_ID",
      "partOfAnyRelation" : true,
      "partOfForeignKey" : true,
      "partOfPrimaryKey" : true,
      "partOfUniqueKey" : false,
      "period" : false,
      "precision" : 10,
      "primaryKey" : false,
      "scale" : 0,
      "sequenceSchema" : null,
      "sqlType" : "number",
      "unique" : false
    }, {
      "columnValue" : {
        "insertable" : true,
        "updatable" : true,
        "defaultValue" : null,
        "type" : "user-defined"
      },
      "constraintList" : null,
      "fieldName" : "productQuantity",
      "foreignKey" : false,
      "generatorType" : "assigned",
      "generatorValue" : null,
      "hidden" : false,
      "javaType" : "integer",
      "length" : 255,
      "name" : "PRODUCT_QUANTITY",
      "nullable" : true,
      "oldName" : "PRODUCT_QUANTITY",
      "partOfAnyRelation" : false,
      "partOfForeignKey" : false,
      "partOfPrimaryKey" : false,
      "partOfUniqueKey" : false,
      "period" : false,
      "precision" : 10,
      "primaryKey" : false,
      "scale" : 0,
      "sequenceSchema" : null,
      "sqlType" : "number",
      "unique" : false
    }, {
      "columnValue" : {
        "insertable" : true,
        "updatable" : true,
        "defaultValue" : null,
        "type" : "user-defined"
      },
      "constraintList" : null,
      "fieldName" : "currentPrice",
      "foreignKey" : false,
      "generatorType" : "assigned",
      "generatorValue" : null,
      "hidden" : false,
      "javaType" : "big_decimal",
      "length" : 255,
      "name" : "CURRENT_PRICE",
      "nullable" : false,
      "oldName" : "CURRENT_PRICE",
      "partOfAnyRelation" : false,
      "partOfForeignKey" : false,
      "partOfPrimaryKey" : false,
      "partOfUniqueKey" : false,
      "period" : false,
      "precision" : 64,
      "primaryKey" : false,
      "scale" : 9,
      "sequenceSchema" : null,
      "sqlType" : "number",
      "unique" : false
    }, {
      "columnValue" : {
        "insertable" : true,
        "updatable" : true,
        "defaultValue" : null,
        "type" : "user-defined"
      },
      "constraintList" : null,
      "fieldName" : "totalPrice",
      "foreignKey" : false,
      "generatorType" : "assigned",
      "generatorValue" : null,
      "hidden" : false,
      "javaType" : "big_decimal",
      "length" : 255,
      "name" : "TOTAL_PRICE",
      "nullable" : true,
      "oldName" : "TOTAL_PRICE",
      "partOfAnyRelation" : false,
      "partOfForeignKey" : false,
      "partOfPrimaryKey" : false,
      "partOfUniqueKey" : false,
      "period" : false,
      "precision" : 64,
      "primaryKey" : false,
      "scale" : 9,
      "sequenceSchema" : null,
      "sqlType" : "number",
      "unique" : false
    } ],
    "constraints" : [ ],
    "entityName" : "CartItems",
    "filter" : null,
    "fullyQualifiedName" : "com.wavemaker.sampleapps.wavekart.eshopping.CartItems",
    "ignoreRefreshAfterInsert" : false,
    "name" : "CART_ITEMS",
    "oldName" : "CART_ITEMS",
    "primaryKey" : {
      "columns" : [ "CART_ID", "PRODUCT_ID" ],
      "composite" : true,
      "generator" : {
        "generatorType" : "assigned",
        "generatorValue" : null,
        "schemaName" : null
      },
      "name" : "SYS_PK_10163",
      "virtual" : false
    },
    "relations" : [ {
      "cardinality" : "ManyToOne",
      "cascadeEnabled" : true,
      "cascadeOptions" : {
        "cascadeRemove" : "REMOVE",
        "cascadeReplace" : false
      },
      "columnsUniqueKey" : false,
      "composite" : false,
      "fetchOptions" : {
        "fetch" : true,
        "columnsFilter" : [ ]
      },
      "fieldName" : "cartDetails",
      "ignored" : false,
      "mappings" : [ {
        "sourceColumn" : "CART_ID",
        "targetColumn" : "CART_ID"
      } ],
      "name" : "SYS_FK_10165",
      "parentFetchOptions" : {
        "fetch" : false,
        "columnsFilter" : [ ]
      },
      "primary" : true,
      "selfRelation" : false,
      "sourceColumnsNotUniqueKey" : true,
      "sourceTable" : "CART_ITEMS",
      "targetColumnsUniqueKey" : false,
      "targetTable" : "CART_DETAILS",
      "valid" : true,
      "virtual" : false
    }, {
      "cardinality" : "ManyToOne",
      "cascadeEnabled" : true,
      "cascadeOptions" : {
        "cascadeRemove" : "REMOVE",
        "cascadeReplace" : false
      },
      "columnsUniqueKey" : false,
      "composite" : false,
      "fetchOptions" : {
        "fetch" : true,
        "columnsFilter" : [ ]
      },
      "fieldName" : "productDetails",
      "ignored" : false,
      "mappings" : [ {
        "sourceColumn" : "PRODUCT_ID",
        "targetColumn" : "PRODUCT_ID"
      } ],
      "name" : "SYS_FK_10164",
      "parentFetchOptions" : {
        "fetch" : false,
        "columnsFilter" : [ ]
      },
      "primary" : true,
      "selfRelation" : false,
      "sourceColumnsNotUniqueKey" : true,
      "sourceTable" : "CART_ITEMS",
      "targetColumnsUniqueKey" : false,
      "targetTable" : "PRODUCT_DETAILS",
      "valid" : true,
      "virtual" : false
    } ],
    "schema" : "PUBLIC",
    "temporals" : [ ],
    "type" : "TABLE"
  }, {
    "catalog" : "PUBLIC",
    "columns" : [ {
      "columnValue" : {
        "insertable" : true,
        "updatable" : true,
        "defaultValue" : null,
        "type" : "user-defined"
      },
      "constraintList" : null,
      "fieldName" : "orderId",
      "foreignKey" : true,
      "generatorType" : "assigned",
      "generatorValue" : null,
      "hidden" : false,
      "javaType" : "integer",
      "length" : 255,
      "name" : "ORDER_ID",
      "nullable" : false,
      "oldName" : "ORDER_ID",
      "partOfAnyRelation" : true,
      "partOfForeignKey" : true,
      "partOfPrimaryKey" : true,
      "partOfUniqueKey" : false,
      "period" : false,
      "precision" : 10,
      "primaryKey" : false,
      "scale" : 0,
      "sequenceSchema" : null,
      "sqlType" : "number",
      "unique" : false
    }, {
      "columnValue" : {
        "insertable" : true,
        "updatable" : true,
        "defaultValue" : null,
        "type" : "user-defined"
      },
      "constraintList" : null,
      "fieldName" : "productId",
      "foreignKey" : true,
      "generatorType" : "assigned",
      "generatorValue" : null,
      "hidden" : false,
      "javaType" : "integer",
      "length" : 255,
      "name" : "PRODUCT_ID",
      "nullable" : false,
      "oldName" : "PRODUCT_ID",
      "partOfAnyRelation" : true,
      "partOfForeignKey" : true,
      "partOfPrimaryKey" : true,
      "partOfUniqueKey" : false,
      "period" : false,
      "precision" : 10,
      "primaryKey" : false,
      "scale" : 0,
      "sequenceSchema" : null,
      "sqlType" : "number",
      "unique" : false
    }, {
      "columnValue" : {
        "insertable" : true,
        "updatable" : true,
        "defaultValue" : null,
        "type" : "user-defined"
      },
      "constraintList" : null,
      "fieldName" : "quantity",
      "foreignKey" : false,
      "generatorType" : "assigned",
      "generatorValue" : null,
      "hidden" : false,
      "javaType" : "integer",
      "length" : 255,
      "name" : "QUANTITY",
      "nullable" : true,
      "oldName" : "QUANTITY",
      "partOfAnyRelation" : false,
      "partOfForeignKey" : false,
      "partOfPrimaryKey" : false,
      "partOfUniqueKey" : false,
      "period" : false,
      "precision" : 10,
      "primaryKey" : false,
      "scale" : 0,
      "sequenceSchema" : null,
      "sqlType" : "number",
      "unique" : false
    }, {
      "columnValue" : {
        "insertable" : true,
        "updatable" : true,
        "defaultValue" : null,
        "type" : "user-defined"
      },
      "constraintList" : null,
      "fieldName" : "pricePerUnit",
      "foreignKey" : false,
      "generatorType" : "assigned",
      "generatorValue" : null,
      "hidden" : false,
      "javaType" : "big_decimal",
      "length" : 255,
      "name" : "PRICE_PER_UNIT",
      "nullable" : true,
      "oldName" : "PRICE_PER_UNIT",
      "partOfAnyRelation" : false,
      "partOfForeignKey" : false,
      "partOfPrimaryKey" : false,
      "partOfUniqueKey" : false,
      "period" : false,
      "precision" : 64,
      "primaryKey" : false,
      "scale" : 9,
      "sequenceSchema" : null,
      "sqlType" : "number",
      "unique" : false
    }, {
      "columnValue" : {
        "insertable" : true,
        "updatable" : true,
        "defaultValue" : null,
        "type" : "user-defined"
      },
      "constraintList" : null,
      "fieldName" : "productLineAmount",
      "foreignKey" : false,
      "generatorType" : "assigned",
      "generatorValue" : null,
      "hidden" : false,
      "javaType" : "big_decimal",
      "length" : 255,
      "name" : "PRODUCT_LINE_AMOUNT",
      "nullable" : true,
      "oldName" : "PRODUCT_LINE_AMOUNT",
      "partOfAnyRelation" : false,
      "partOfForeignKey" : false,
      "partOfPrimaryKey" : false,
      "partOfUniqueKey" : false,
      "period" : false,
      "precision" : 64,
      "primaryKey" : false,
      "scale" : 9,
      "sequenceSchema" : null,
      "sqlType" : "number",
      "unique" : false
    } ],
    "constraints" : [ ],
    "entityName" : "OrderLineItems",
    "filter" : null,
    "fullyQualifiedName" : "com.wavemaker.sampleapps.wavekart.eshopping.OrderLineItems",
    "ignoreRefreshAfterInsert" : false,
    "name" : "ORDER_LINE_ITEMS",
    "oldName" : "ORDER_LINE_ITEMS",
    "primaryKey" : {
      "columns" : [ "ORDER_ID", "PRODUCT_ID" ],
      "composite" : true,
      "generator" : {
        "generatorType" : "assigned",
        "generatorValue" : null,
        "schemaName" : null
      },
      "name" : "SYS_PK_10194",
      "virtual" : false
    },
    "relations" : [ {
      "cardinality" : "ManyToOne",
      "cascadeEnabled" : true,
      "cascadeOptions" : {
        "cascadeRemove" : "REMOVE",
        "cascadeReplace" : false
      },
      "columnsUniqueKey" : false,
      "composite" : false,
      "fetchOptions" : {
        "fetch" : true,
        "columnsFilter" : [ ]
      },
      "fieldName" : "orders",
      "ignored" : false,
      "mappings" : [ {
        "sourceColumn" : "ORDER_ID",
        "targetColumn" : "ORDER_ID"
      } ],
      "name" : "SYS_FK_10196",
      "parentFetchOptions" : {
        "fetch" : false,
        "columnsFilter" : [ ]
      },
      "primary" : true,
      "selfRelation" : false,
      "sourceColumnsNotUniqueKey" : true,
      "sourceTable" : "ORDER_LINE_ITEMS",
      "targetColumnsUniqueKey" : false,
      "targetTable" : "ORDERS",
      "valid" : true,
      "virtual" : false
    }, {
      "cardinality" : "ManyToOne",
      "cascadeEnabled" : true,
      "cascadeOptions" : {
        "cascadeRemove" : "REMOVE",
        "cascadeReplace" : false
      },
      "columnsUniqueKey" : false,
      "composite" : false,
      "fetchOptions" : {
        "fetch" : true,
        "columnsFilter" : [ ]
      },
      "fieldName" : "productDetails",
      "ignored" : false,
      "mappings" : [ {
        "sourceColumn" : "PRODUCT_ID",
        "targetColumn" : "PRODUCT_ID"
      } ],
      "name" : "SYS_FK_10195",
      "parentFetchOptions" : {
        "fetch" : false,
        "columnsFilter" : [ ]
      },
      "primary" : true,
      "selfRelation" : false,
      "sourceColumnsNotUniqueKey" : true,
      "sourceTable" : "ORDER_LINE_ITEMS",
      "targetColumnsUniqueKey" : false,
      "targetTable" : "PRODUCT_DETAILS",
      "valid" : true,
      "virtual" : false
    } ],
    "schema" : "PUBLIC",
    "temporals" : [ ],
    "type" : "TABLE"
  }, {
    "catalog" : "PUBLIC",
    "columns" : [ {
      "columnValue" : {
        "insertable" : true,
        "updatable" : true,
        "defaultValue" : null,
        "type" : "user-defined"
      },
      "constraintList" : null,
      "fieldName" : "orderId",
      "foreignKey" : false,
      "generatorType" : "identity",
      "generatorValue" : null,
      "hidden" : false,
      "javaType" : "integer",
      "length" : 255,
      "name" : "ORDER_ID",
      "nullable" : false,
      "oldName" : "ORDER_ID",
      "partOfAnyRelation" : false,
      "partOfForeignKey" : false,
      "partOfPrimaryKey" : true,
      "partOfUniqueKey" : true,
      "period" : false,
      "precision" : 10,
      "primaryKey" : true,
      "scale" : 0,
      "sequenceSchema" : null,
      "sqlType" : "number",
      "unique" : true
    }, {
      "columnValue" : {
        "insertable" : true,
        "updatable" : true,
        "defaultValue" : null,
        "type" : "user-defined"
      },
      "constraintList" : null,
      "fieldName" : "userId",
      "foreignKey" : true,
      "generatorType" : "assigned",
      "generatorValue" : null,
      "hidden" : false,
      "javaType" : "integer",
      "length" : 255,
      "name" : "USER_ID",
      "nullable" : false,
      "oldName" : "USER_ID",
      "partOfAnyRelation" : true,
      "partOfForeignKey" : true,
      "partOfPrimaryKey" : false,
      "partOfUniqueKey" : false,
      "period" : false,
      "precision" : 10,
      "primaryKey" : false,
      "scale" : 0,
      "sequenceSchema" : null,
      "sqlType" : "number",
      "unique" : false
    }, {
      "columnValue" : {
        "insertable" : true,
        "updatable" : true,
        "defaultValue" : null,
        "type" : "user-defined"
      },
      "constraintList" : null,
      "fieldName" : "userAddressId",
      "foreignKey" : true,
      "generatorType" : "assigned",
      "generatorValue" : null,
      "hidden" : false,
      "javaType" : "integer",
      "length" : 255,
      "name" : "USER_ADDRESS_ID",
      "nullable" : false,
      "oldName" : "USER_ADDRESS_ID",
      "partOfAnyRelation" : true,
      "partOfForeignKey" : true,
      "partOfPrimaryKey" : false,
      "partOfUniqueKey" : false,
      "period" : false,
      "precision" : 10,
      "primaryKey" : false,
      "scale" : 0,
      "sequenceSchema" : null,
      "sqlType" : "number",
      "unique" : false
    }, {
      "columnValue" : {
        "insertable" : true,
        "updatable" : true,
        "defaultValue" : null,
        "type" : "user-defined"
      },
      "constraintList" : null,
      "fieldName" : "totalQuantity",
      "foreignKey" : false,
      "generatorType" : "assigned",
      "generatorValue" : null,
      "hidden" : false,
      "javaType" : "integer",
      "length" : 255,
      "name" : "TOTAL_QUANTITY",
      "nullable" : true,
      "oldName" : "TOTAL_QUANTITY",
      "partOfAnyRelation" : false,
      "partOfForeignKey" : false,
      "partOfPrimaryKey" : false,
      "partOfUniqueKey" : false,
      "period" : false,
      "precision" : 10,
      "primaryKey" : false,
      "scale" : 0,
      "sequenceSchema" : null,
      "sqlType" : "number",
      "unique" : false
    }, {
      "columnValue" : {
        "insertable" : true,
        "updatable" : true,
        "defaultValue" : null,
        "type" : "user-defined"
      },
      "constraintList" : null,
      "fieldName" : "totalPrice",
      "foreignKey" : false,
      "generatorType" : "assigned",
      "generatorValue" : null,
      "hidden" : false,
      "javaType" : "big_decimal",
      "length" : 255,
      "name" : "TOTAL_PRICE",
      "nullable" : true,
      "oldName" : "TOTAL_PRICE",
      "partOfAnyRelation" : false,
      "partOfForeignKey" : false,
      "partOfPrimaryKey" : false,
      "partOfUniqueKey" : false,
      "period" : false,
      "precision" : 64,
      "primaryKey" : false,
      "scale" : 9,
      "sequenceSchema" : null,
      "sqlType" : "number",
      "unique" : false
    }, {
      "columnValue" : {
        "insertable" : true,
        "updatable" : true,
        "defaultValue" : null,
        "type" : "user-defined"
      },
      "constraintList" : null,
      "fieldName" : "orderDate",
      "foreignKey" : false,
      "generatorType" : "assigned",
      "generatorValue" : null,
      "hidden" : false,
      "javaType" : "timestamp",
      "length" : 26,
      "name" : "ORDER_DATE",
      "nullable" : false,
      "oldName" : "ORDER_DATE",
      "partOfAnyRelation" : false,
      "partOfForeignKey" : false,
      "partOfPrimaryKey" : false,
      "partOfUniqueKey" : false,
      "period" : false,
      "precision" : 19,
      "primaryKey" : false,
      "scale" : 2,
      "sequenceSchema" : null,
      "sqlType" : "timestamp",
      "unique" : false
    }, {
      "columnValue" : {
        "insertable" : true,
        "updatable" : true,
        "defaultValue" : null,
        "type" : "user-defined"
      },
      "constraintList" : null,
      "fieldName" : "status",
      "foreignKey" : false,
      "generatorType" : "assigned",
      "generatorValue" : null,
      "hidden" : false,
      "javaType" : "string",
      "length" : 255,
      "name" : "STATUS",
      "nullable" : false,
      "oldName" : "STATUS",
      "partOfAnyRelation" : false,
      "partOfForeignKey" : false,
      "partOfPrimaryKey" : false,
      "partOfUniqueKey" : false,
      "period" : false,
      "precision" : 19,
      "primaryKey" : false,
      "scale" : 2,
      "sequenceSchema" : null,
      "sqlType" : "string",
      "unique" : false
    } ],
    "constraints" : [ ],
    "entityName" : "Orders",
    "filter" : null,
    "fullyQualifiedName" : "com.wavemaker.sampleapps.wavekart.eshopping.Orders",
    "ignoreRefreshAfterInsert" : false,
    "name" : "ORDERS",
    "oldName" : "ORDERS",
    "primaryKey" : {
      "columns" : [ "ORDER_ID" ],
      "composite" : false,
      "generator" : {
        "generatorType" : "identity",
        "generatorValue" : null,
        "schemaName" : null
      },
      "name" : "SYS_PK_10175",
      "virtual" : false
    },
    "relations" : [ {
      "cardinality" : "ManyToOne",
      "cascadeEnabled" : true,
      "cascadeOptions" : {
        "cascadeRemove" : "REMOVE",
        "cascadeReplace" : false
      },
      "columnsUniqueKey" : false,
      "composite" : false,
      "fetchOptions" : {
        "fetch" : true,
        "columnsFilter" : [ ]
      },
      "fieldName" : "userAddressDetails",
      "ignored" : false,
      "mappings" : [ {
        "sourceColumn" : "USER_ADDRESS_ID",
        "targetColumn" : "USER_ADDRESSS_ID"
      } ],
      "name" : "SYS_FK_10181",
      "parentFetchOptions" : {
        "fetch" : false,
        "columnsFilter" : [ ]
      },
      "primary" : true,
      "selfRelation" : false,
      "sourceColumnsNotUniqueKey" : true,
      "sourceTable" : "ORDERS",
      "targetColumnsUniqueKey" : false,
      "targetTable" : "USER_ADDRESS_DETAILS",
      "valid" : true,
      "virtual" : false
    }, {
      "cardinality" : "ManyToOne",
      "cascadeEnabled" : true,
      "cascadeOptions" : {
        "cascadeRemove" : "REMOVE",
        "cascadeReplace" : false
      },
      "columnsUniqueKey" : false,
      "composite" : false,
      "fetchOptions" : {
        "fetch" : true,
        "columnsFilter" : [ ]
      },
      "fieldName" : "userDetails",
      "ignored" : false,
      "mappings" : [ {
        "sourceColumn" : "USER_ID",
        "targetColumn" : "USER_ID"
      } ],
      "name" : "SYS_FK_10180",
      "parentFetchOptions" : {
        "fetch" : false,
        "columnsFilter" : [ ]
      },
      "primary" : true,
      "selfRelation" : false,
      "sourceColumnsNotUniqueKey" : true,
      "sourceTable" : "ORDERS",
      "targetColumnsUniqueKey" : false,
      "targetTable" : "USER_DETAILS",
      "valid" : true,
      "virtual" : false
    } ],
    "schema" : "PUBLIC",
    "temporals" : [ ],
    "type" : "TABLE"
  }, {
    "catalog" : "PUBLIC",
    "columns" : [ {
      "columnValue" : {
        "insertable" : true,
        "updatable" : true,
        "defaultValue" : null,
        "type" : "user-defined"
      },
      "constraintList" : null,
      "fieldName" : "cartId",
      "foreignKey" : false,
      "generatorType" : "assigned",
      "generatorValue" : null,
      "hidden" : false,
      "javaType" : "integer",
      "length" : 255,
      "name" : "CART_ID",
      "nullable" : false,
      "oldName" : "CART_ID",
      "partOfAnyRelation" : false,
      "partOfForeignKey" : false,
      "partOfPrimaryKey" : true,
      "partOfUniqueKey" : true,
      "period" : false,
      "precision" : 10,
      "primaryKey" : true,
      "scale" : 0,
      "sequenceSchema" : null,
      "sqlType" : "number",
      "unique" : true
    }, {
      "columnValue" : {
        "insertable" : true,
        "updatable" : true,
        "defaultValue" : null,
        "type" : "user-defined"
      },
      "constraintList" : null,
      "fieldName" : "userId",
      "foreignKey" : true,
      "generatorType" : "assigned",
      "generatorValue" : null,
      "hidden" : false,
      "javaType" : "integer",
      "length" : 255,
      "name" : "USER_ID",
      "nullable" : false,
      "oldName" : "USER_ID",
      "partOfAnyRelation" : true,
      "partOfForeignKey" : true,
      "partOfPrimaryKey" : false,
      "partOfUniqueKey" : true,
      "period" : false,
      "precision" : 10,
      "primaryKey" : false,
      "scale" : 0,
      "sequenceSchema" : null,
      "sqlType" : "number",
      "unique" : true
    } ],
    "constraints" : [ {
      "columns" : [ "USER_ID" ],
      "composite" : false,
      "name" : "SYS_IDX_SYS_CT_10152_10157",
      "schemaName" : null,
      "type" : "UNIQUE",
      "virtual" : false
    } ],
    "entityName" : "CartDetails",
    "filter" : null,
    "fullyQualifiedName" : "com.wavemaker.sampleapps.wavekart.eshopping.CartDetails",
    "ignoreRefreshAfterInsert" : false,
    "name" : "CART_DETAILS",
    "oldName" : "CART_DETAILS",
    "primaryKey" : {
      "columns" : [ "CART_ID" ],
      "composite" : false,
      "generator" : {
        "generatorType" : "assigned",
        "generatorValue" : null,
        "schemaName" : null
      },
      "name" : "SYS_PK_10150",
      "virtual" : false
    },
    "relations" : [ {
      "cardinality" : "OneToOne",
      "cascadeEnabled" : true,
      "cascadeOptions" : {
        "cascadeRemove" : "REMOVE",
        "cascadeReplace" : false
      },
      "columnsUniqueKey" : true,
      "composite" : false,
      "fetchOptions" : {
        "fetch" : true,
        "columnsFilter" : [ ]
      },
      "fieldName" : "userDetails",
      "ignored" : false,
      "mappings" : [ {
        "sourceColumn" : "USER_ID",
        "targetColumn" : "USER_ID"
      } ],
      "name" : "SYS_FK_10153",
      "parentFetchOptions" : {
        "fetch" : false,
        "columnsFilter" : [ ]
      },
      "primary" : true,
      "selfRelation" : false,
      "sourceColumnsNotUniqueKey" : false,
      "sourceTable" : "CART_DETAILS",
      "targetColumnsUniqueKey" : false,
      "targetTable" : "USER_DETAILS",
      "valid" : true,
      "virtual" : false
    } ],
    "schema" : "PUBLIC",
    "temporals" : [ ],
    "type" : "TABLE"
  }, {
    "catalog" : "PUBLIC",
    "columns" : [ {
      "columnValue" : {
        "insertable" : true,
        "updatable" : true,
        "defaultValue" : null,
        "type" : "user-defined"
      },
      "constraintList" : null,
      "fieldName" : "userAddresssId",
      "foreignKey" : false,
      "generatorType" : "identity",
      "generatorValue" : null,
      "hidden" : false,
      "javaType" : "integer",
      "length" : 255,
      "name" : "USER_ADDRESSS_ID",
      "nullable" : false,
      "oldName" : "USER_ADDRESSS_ID",
      "partOfAnyRelation" : false,
      "partOfForeignKey" : false,
      "partOfPrimaryKey" : true,
      "partOfUniqueKey" : true,
      "period" : false,
      "precision" : 10,
      "primaryKey" : true,
      "scale" : 0,
      "sequenceSchema" : null,
      "sqlType" : "number",
      "unique" : true
    }, {
      "columnValue" : {
        "insertable" : true,
        "updatable" : true,
        "defaultValue" : null,
        "type" : "user-defined"
      },
      "constraintList" : null,
      "fieldName" : "userId",
      "foreignKey" : true,
      "generatorType" : "assigned",
      "generatorValue" : null,
      "hidden" : false,
      "javaType" : "integer",
      "length" : 255,
      "name" : "USER_ID",
      "nullable" : false,
      "oldName" : "USER_ID",
      "partOfAnyRelation" : true,
      "partOfForeignKey" : true,
      "partOfPrimaryKey" : false,
      "partOfUniqueKey" : false,
      "period" : false,
      "precision" : 10,
      "primaryKey" : false,
      "scale" : 0,
      "sequenceSchema" : null,
      "sqlType" : "number",
      "unique" : false
    }, {
      "columnValue" : {
        "insertable" : true,
        "updatable" : true,
        "defaultValue" : null,
        "type" : "user-defined"
      },
      "constraintList" : null,
      "fieldName" : "address",
      "foreignKey" : false,
      "generatorType" : "assigned",
      "generatorValue" : null,
      "hidden" : false,
      "javaType" : "string",
      "length" : 255,
      "name" : "ADDRESS",
      "nullable" : false,
      "oldName" : "ADDRESS",
      "partOfAnyRelation" : false,
      "partOfForeignKey" : false,
      "partOfPrimaryKey" : false,
      "partOfUniqueKey" : false,
      "period" : false,
      "precision" : 19,
      "primaryKey" : false,
      "scale" : 2,
      "sequenceSchema" : null,
      "sqlType" : "string",
      "unique" : false
    }, {
      "columnValue" : {
        "insertable" : true,
        "updatable" : true,
        "defaultValue" : null,
        "type" : "user-defined"
      },
      "constraintList" : null,
      "fieldName" : "city",
      "foreignKey" : false,
      "generatorType" : "assigned",
      "generatorValue" : null,
      "hidden" : false,
      "javaType" : "string",
      "length" : 255,
      "name" : "CITY",
      "nullable" : false,
      "oldName" : "CITY",
      "partOfAnyRelation" : false,
      "partOfForeignKey" : false,
      "partOfPrimaryKey" : false,
      "partOfUniqueKey" : false,
      "period" : false,
      "precision" : 19,
      "primaryKey" : false,
      "scale" : 2,
      "sequenceSchema" : null,
      "sqlType" : "string",
      "unique" : false
    }, {
      "columnValue" : {
        "insertable" : true,
        "updatable" : true,
        "defaultValue" : null,
        "type" : "user-defined"
      },
      "constraintList" : null,
      "fieldName" : "state",
      "foreignKey" : false,
      "generatorType" : "assigned",
      "generatorValue" : null,
      "hidden" : false,
      "javaType" : "string",
      "length" : 255,
      "name" : "STATE",
      "nullable" : false,
      "oldName" : "STATE",
      "partOfAnyRelation" : false,
      "partOfForeignKey" : false,
      "partOfPrimaryKey" : false,
      "partOfUniqueKey" : false,
      "period" : false,
      "precision" : 19,
      "primaryKey" : false,
      "scale" : 2,
      "sequenceSchema" : null,
      "sqlType" : "string",
      "unique" : false
    }, {
      "columnValue" : {
        "insertable" : true,
        "updatable" : true,
        "defaultValue" : null,
        "type" : "user-defined"
      },
      "constraintList" : null,
      "fieldName" : "country",
      "foreignKey" : false,
      "generatorType" : "assigned",
      "generatorValue" : null,
      "hidden" : false,
      "javaType" : "string",
      "length" : 255,
      "name" : "COUNTRY",
      "nullable" : false,
      "oldName" : "COUNTRY",
      "partOfAnyRelation" : false,
      "partOfForeignKey" : false,
      "partOfPrimaryKey" : false,
      "partOfUniqueKey" : false,
      "period" : false,
      "precision" : 19,
      "primaryKey" : false,
      "scale" : 2,
      "sequenceSchema" : null,
      "sqlType" : "string",
      "unique" : false
    }, {
      "columnValue" : {
        "insertable" : true,
        "updatable" : true,
        "defaultValue" : null,
        "type" : "user-defined"
      },
      "constraintList" : null,
      "fieldName" : "pincode",
      "foreignKey" : false,
      "generatorType" : "assigned",
      "generatorValue" : null,
      "hidden" : false,
      "javaType" : "integer",
      "length" : 255,
      "name" : "PINCODE",
      "nullable" : false,
      "oldName" : "PINCODE",
      "partOfAnyRelation" : false,
      "partOfForeignKey" : false,
      "partOfPrimaryKey" : false,
      "partOfUniqueKey" : false,
      "period" : false,
      "precision" : 10,
      "primaryKey" : false,
      "scale" : 0,
      "sequenceSchema" : null,
      "sqlType" : "number",
      "unique" : false
    } ],
    "constraints" : [ ],
    "entityName" : "UserAddressDetails",
    "filter" : null,
    "fullyQualifiedName" : "com.wavemaker.sampleapps.wavekart.eshopping.UserAddressDetails",
    "ignoreRefreshAfterInsert" : false,
    "name" : "USER_ADDRESS_DETAILS",
    "oldName" : "USER_ADDRESS_DETAILS",
    "primaryKey" : {
      "columns" : [ "USER_ADDRESSS_ID" ],
      "composite" : false,
      "generator" : {
        "generatorType" : "identity",
        "generatorValue" : null,
        "schemaName" : null
      },
      "name" : "SYS_PK_10131",
      "virtual" : false
    },
    "relations" : [ {
      "cardinality" : "ManyToOne",
      "cascadeEnabled" : true,
      "cascadeOptions" : {
        "cascadeRemove" : "REMOVE",
        "cascadeReplace" : false
      },
      "columnsUniqueKey" : false,
      "composite" : false,
      "fetchOptions" : {
        "fetch" : true,
        "columnsFilter" : [ ]
      },
      "fieldName" : "userDetails",
      "ignored" : false,
      "mappings" : [ {
        "sourceColumn" : "USER_ID",
        "targetColumn" : "USER_ID"
      } ],
      "name" : "SYS_FK_10138",
      "parentFetchOptions" : {
        "fetch" : false,
        "columnsFilter" : [ ]
      },
      "primary" : true,
      "selfRelation" : false,
      "sourceColumnsNotUniqueKey" : true,
      "sourceTable" : "USER_ADDRESS_DETAILS",
      "targetColumnsUniqueKey" : false,
      "targetTable" : "USER_DETAILS",
      "valid" : true,
      "virtual" : false
    } ],
    "schema" : "PUBLIC",
    "temporals" : [ ],
    "type" : "TABLE"
  } ]
}